drf_tools/__init__.py
drf_tools/exceptions.py
drf_tools/fields.py
drf_tools/filters.py
drf_tools/renderers.py
drf_tools/routers.py
drf_tools/serializers.py
drf_tools/utils.py
drf_tools/views.py
drf_tools/auth/__init__.py
drf_tools/auth/authentications.py
drf_tools/auth/disablecsrf.py
drf_tools/auth/filters.py
drf_tools/auth/models.py
drf_tools/auth/permissions.py
drf_tools/auth/permissionservice.py
drf_tools/auth/serializers.py
drf_tools/auth/views.py
drf_tools/test/__init__.py
drf_tools/test/base.py
drf_tools/test/utils.py
drf_tools/validation/__init__.py
drf_tools/validation/base.py
drf_tools/validation/registry.py
drf_tools/validation/request.py
drf_tools/validation/views.py
drf_tools-0.10.0.dist-info/LICENSE.md
drf_tools-0.10.0.dist-info/METADATA
drf_tools-0.10.0.dist-info/WHEEL
drf_tools-0.10.0.dist-info/top_level.txt
drf_tools-0.10.0.dist-info/RECORD
